MANIFEST.in
README.md
REFERENCE.md
VERSION.txt
setup.py
dataflows_shell/__init__.py
dataflows_shell/cli.py
dataflows_shell.egg-info/PKG-INFO
dataflows_shell.egg-info/SOURCES.txt
dataflows_shell.egg-info/dependency_links.txt
dataflows_shell.egg-info/entry_points.txt
dataflows_shell.egg-info/requires.txt
dataflows_shell.egg-info/top_level.txt
dataflows_shell/processors/__init__.py
dataflows_shell/processors/add_field.py
dataflows_shell/processors/checkpoint.py
dataflows_shell/processors/ckan.py
dataflows_shell/processors/exec.py
dataflows_shell/processors/kubectl.py
dataflows_shell/processors/ls.py