Metadata-Version: 1.0
Name: dataflows-shell
Version: 0.0.6
Summary: Integrate DataFlows with shell scripts
Home-page: https://github.com/OriHoch/dataflows-shell
Author: Ori Hoch
Author-email: ori@uumpa.com
License: MIT
Platform: UNKNOWN
